implicit/__init__.py
implicit/_nearest_neighbours.cpython-311-aarch64-linux-gnu.so
implicit/als.py
implicit/approximate_als.py
implicit/bpr.py
implicit/evaluation.cpython-311-aarch64-linux-gnu.so
implicit/lmf.py
implicit/nearest_neighbours.py
implicit/recommender_base.py
implicit/utils.py
implicit/ann/__init__.py
implicit/ann/annoy.py
implicit/ann/faiss.py
implicit/ann/nmslib.py
implicit/cpu/__init__.py
implicit/cpu/_als.cpython-311-aarch64-linux-gnu.so
implicit/cpu/als.py
implicit/cpu/bpr.cpython-311-aarch64-linux-gnu.so
implicit/cpu/lmf.cpython-311-aarch64-linux-gnu.so
implicit/cpu/matrix_factorization_base.py
implicit/cpu/topk.cpython-311-aarch64-linux-gnu.so
implicit/datasets/__init__.py
implicit/datasets/_download.py
implicit/datasets/lastfm.py
implicit/datasets/million_song_dataset.py
implicit/datasets/movielens.py
implicit/datasets/reddit.py
implicit/datasets/sketchfab.py
implicit/gpu/__init__.py
implicit/gpu/als.py
implicit/gpu/bpr.py
implicit/gpu/matrix_factorization_base.py
wbimplicit-0.6.2.1.dist-info/LICENSE
wbimplicit-0.6.2.1.dist-info/METADATA
wbimplicit-0.6.2.1.dist-info/WHEEL
wbimplicit-0.6.2.1.dist-info/top_level.txt
wbimplicit-0.6.2.1.dist-info/RECORD
